{"business_id": "q-Pc4j3mIzCfD-3eOs71jg", "full_address": "Edgar-Heller-Str. 19\n76227 Karlsruhe", "hours": {}, "open": true, "categories": ["Fitness & Instruction", "Police Departments", "Martial Arts", "Active Life", "Public Services & Government", "Sports Clubs"], "city": "Karlsruhe", "review_count": 3, "name": "Polizeisportverein Karlsruhe e.V.", "neighborhoods": [], "longitude": 8.43041, "state": "BW", "stars": 5.0, "latitude": 48.9947, "attributes": {"Good For Dancing": false, "Noise Level": "quiet", "Coat Check": false, "Music": {"dj": false}, "Outdoor Seating": true, "Parking": {"garage": false, "street": false, "validated": false, "lot": false, "valet": false}, "Ambience": {"romantic": false, "intimate": false, "classy": false, "hipster": false, "divey": false, "touristy": false, "trendy": false, "upscale": false, "casual": false}, "Has TV": true, "Accepts Credit Cards": false, "Good for Kids": true, "Good For Groups": true, "Price Range": 1}, "type": "business"}
{"business_id": "mi6HyXkJK9Adzq-xti3oiA", "full_address": "Kaiserallee 3\n76133 Karlsruhe", "hours": {}, "open": false, "categories": ["Active Life", "Dance Studios", "Nightlife", "Dance Clubs", "Fitness & Instruction"], "city": "Karlsruhe", "review_count": 9, "name": "Discothek Unversch\u00e4mt", "neighborhoods": [], "longitude": 8.38676, "state": "BW", "stars": 4.0, "latitude": 49.0103, "attributes": {"Coat Check": true, "Alcohol": "beer_and_wine", "Attire": "casual", "Has TV": false, "Smoking": "outdoor", "Happy Hour": true, "Wheelchair Accessible": true, "Outdoor Seating": false, "Parking": {"garage": false, "validated": false, "street": false, "lot": false, "valet": false}, "Music": {"dj": true, "background_music": false, "karaoke": false, "live": false, "video": false, "jukebox": false}, "Accepts Credit Cards": false, "Good For Groups": false, "Price Range": 2}, "type": "business"}
{"business_id": "G5u6zPWAwNnm_JvbFx05yA", "full_address": "Gerwigstrasse 66a\n76131 Karlsruhe", "hours": {"Monday": {"close": "23:00", "open": "06:00"}, "Tuesday": {"close": "23:00", "open": "06:00"}, "Friday": {"close": "22:00", "open": "06:00"}, "Wednesday": {"close": "23:00", "open": "06:00"}, "Thursday": {"close": "23:00", "open": "06:00"}, "Sunday": {"close": "20:00", "open": "10:00"}, "Saturday": {"close": "20:00", "open": "10:00"}}, "open": true, "categories": ["Active Life", "Gyms", "Fitness & Instruction"], "city": "Karlsruhe", "review_count": 8, "name": "Fitness First", "neighborhoods": [], "longitude": 8.43822, "state": "BW", "stars": 2.0, "latitude": 49.00618, "attributes": {"Good for Kids": false, "Price Range": 3}, "type": "business"}
{"business_id": "1t-91ideKB7wTRRmqp3GUA", "full_address": "Gerwigstr. 69\n76131 Karlsruhe", "hours": {"Monday": {"close": "23:00", "open": "07:00"}, "Tuesday": {"close": "23:00", "open": "09:00"}, "Friday": {"close": "23:00", "open": "09:00"}, "Wednesday": {"close": "23:00", "open": "07:00"}, "Thursday": {"close": "23:00", "open": "09:00"}, "Sunday": {"close": "20:00", "open": "10:00"}, "Saturday": {"close": "18:00", "open": "09:00"}}, "open": true, "categories": ["Active Life", "Yoga", "Pilates", "Gyms", "Fitness & Instruction"], "city": "Karlsruhe", "review_count": 3, "name": "ActivSports", "neighborhoods": [], "longitude": 8.4303821, "state": "BW", "stars": 4.0, "latitude": 49.0116951, "attributes": {"Parking": {"garage": false, "validated": false, "street": false, "lot": false, "valet": false}, "Price Range": 1}, "type": "business"}
{"business_id": "VIrt4ovZQRKrUuAelX1Avg", "full_address": "R\u00fcppurrer Str. 1\n76137 Karlsruhe", "hours": {}, "open": true, "categories": ["Active Life", "Pilates", "Gyms", "Fitness & Instruction"], "city": "Karlsruhe", "review_count": 4, "name": "Venice Beach", "neighborhoods": [], "longitude": 8.411515, "state": "BW", "stars": 3.0, "latitude": 49.005771, "attributes": {"Parking": {"garage": false, "validated": false, "street": false, "lot": false, "valet": false}, "Good for Kids": false, "Price Range": 1}, "type": "business"}
{"business_id": "q-Pc4j3mIzCfD-3eOs71jg", "full_address": "Edgar-Heller-Str. 19\n76227 Karlsruhe", "hours": {}, "open": true, "categories": ["Fitness & Instruction", "Police Departments", "Martial Arts", "Active Life", "Public Services & Government", "Sports Clubs"], "city": "Karlsruhe", "review_count": 3, "name": "Polizeisportverein Karlsruhe e.V.", "neighborhoods": [], "longitude": 8.43041, "state": "BW", "stars": 5.0, "latitude": 48.9947, "attributes": {"Good For Dancing": false, "Noise Level": "quiet", "Coat Check": false, "Music": {"dj": false}, "Outdoor Seating": true, "Parking": {"garage": false, "street": false, "validated": false, "lot": false, "valet": false}, "Ambience": {"romantic": false, "intimate": false, "classy": false, "hipster": false, "divey": false, "touristy": false, "trendy": false, "upscale": false, "casual": false}, "Has TV": true, "Accepts Credit Cards": false, "Good for Kids": true, "Good For Groups": true, "Price Range": 1}, "type": "business"}
{"business_id": "mi6HyXkJK9Adzq-xti3oiA", "full_address": "Kaiserallee 3\n76133 Karlsruhe", "hours": {}, "open": false, "categories": ["Active Life", "Dance Studios", "Nightlife", "Dance Clubs", "Fitness & Instruction"], "city": "Karlsruhe", "review_count": 9, "name": "Discothek Unversch\u00e4mt", "neighborhoods": [], "longitude": 8.38676, "state": "BW", "stars": 4.0, "latitude": 49.0103, "attributes": {"Coat Check": true, "Alcohol": "beer_and_wine", "Attire": "casual", "Has TV": false, "Smoking": "outdoor", "Happy Hour": true, "Wheelchair Accessible": true, "Outdoor Seating": false, "Parking": {"garage": false, "validated": false, "street": false, "lot": false, "valet": false}, "Music": {"dj": true, "background_music": false, "karaoke": false, "live": false, "video": false, "jukebox": false}, "Accepts Credit Cards": false, "Good For Groups": false, "Price Range": 2}, "type": "business"}
{"business_id": "G5u6zPWAwNnm_JvbFx05yA", "full_address": "Gerwigstrasse 66a\n76131 Karlsruhe", "hours": {"Monday": {"close": "23:00", "open": "06:00"}, "Tuesday": {"close": "23:00", "open": "06:00"}, "Friday": {"close": "22:00", "open": "06:00"}, "Wednesday": {"close": "23:00", "open": "06:00"}, "Thursday": {"close": "23:00", "open": "06:00"}, "Sunday": {"close": "20:00", "open": "10:00"}, "Saturday": {"close": "20:00", "open": "10:00"}}, "open": true, "categories": ["Active Life", "Gyms", "Fitness & Instruction"], "city": "Karlsruhe", "review_count": 8, "name": "Fitness First", "neighborhoods": [], "longitude": 8.43822, "state": "BW", "stars": 2.0, "latitude": 49.00618, "attributes": {"Good for Kids": false, "Price Range": 3}, "type": "business"}
{"business_id": "1t-91ideKB7wTRRmqp3GUA", "full_address": "Gerwigstr. 69\n76131 Karlsruhe", "hours": {"Monday": {"close": "23:00", "open": "07:00"}, "Tuesday": {"close": "23:00", "open": "09:00"}, "Friday": {"close": "23:00", "open": "09:00"}, "Wednesday": {"close": "23:00", "open": "07:00"}, "Thursday": {"close": "23:00", "open": "09:00"}, "Sunday": {"close": "20:00", "open": "10:00"}, "Saturday": {"close": "18:00", "open": "09:00"}}, "open": true, "categories": ["Active Life", "Yoga", "Pilates", "Gyms", "Fitness & Instruction"], "city": "Karlsruhe", "review_count": 3, "name": "ActivSports", "neighborhoods": [], "longitude": 8.4303821, "state": "BW", "stars": 4.0, "latitude": 49.0116951, "attributes": {"Parking": {"garage": false, "validated": false, "street": false, "lot": false, "valet": false}, "Price Range": 1}, "type": "business"}
{"business_id": "VIrt4ovZQRKrUuAelX1Avg", "full_address": "R\u00fcppurrer Str. 1\n76137 Karlsruhe", "hours": {}, "open": true, "categories": ["Active Life", "Pilates", "Gyms", "Fitness & Instruction"], "city": "Karlsruhe", "review_count": 4, "name": "Venice Beach", "neighborhoods": [], "longitude": 8.411515, "state": "BW", "stars": 3.0, "latitude": 49.005771, "attributes": {"Parking": {"garage": false, "validated": false, "street": false, "lot": false, "valet": false}, "Good for Kids": false, "Price Range": 1}, "type": "business"}
{"business_id": "q-Pc4j3mIzCfD-3eOs71jg", "full_address": "Edgar-Heller-Str. 19\n76227 Karlsruhe", "hours": {}, "open": true, "categories": ["Fitness & Instruction", "Police Departments", "Martial Arts", "Active Life", "Public Services & Government", "Sports Clubs"], "city": "Karlsruhe", "review_count": 3, "name": "Polizeisportverein Karlsruhe e.V.", "neighborhoods": [], "longitude": 8.43041, "state": "BW", "stars": 5.0, "latitude": 48.9947, "attributes": {"Good For Dancing": false, "Noise Level": "quiet", "Coat Check": false, "Music": {"dj": false}, "Outdoor Seating": true, "Parking": {"garage": false, "street": false, "validated": false, "lot": false, "valet": false}, "Ambience": {"romantic": false, "intimate": false, "classy": false, "hipster": false, "divey": false, "touristy": false, "trendy": false, "upscale": false, "casual": false}, "Has TV": true, "Accepts Credit Cards": false, "Good for Kids": true, "Good For Groups": true, "Price Range": 1}, "type": "business"}
{"business_id": "mi6HyXkJK9Adzq-xti3oiA", "full_address": "Kaiserallee 3\n76133 Karlsruhe", "hours": {}, "open": false, "categories": ["Active Life", "Dance Studios", "Nightlife", "Dance Clubs", "Fitness & Instruction"], "city": "Karlsruhe", "review_count": 9, "name": "Discothek Unversch\u00e4mt", "neighborhoods": [], "longitude": 8.38676, "state": "BW", "stars": 4.0, "latitude": 49.0103, "attributes": {"Coat Check": true, "Alcohol": "beer_and_wine", "Attire": "casual", "Has TV": false, "Smoking": "outdoor", "Happy Hour": true, "Wheelchair Accessible": true, "Outdoor Seating": false, "Parking": {"garage": false, "validated": false, "street": false, "lot": false, "valet": false}, "Music": {"dj": true, "background_music": false, "karaoke": false, "live": false, "video": false, "jukebox": false}, "Accepts Credit Cards": false, "Good For Groups": false, "Price Range": 2}, "type": "business"}
{"business_id": "G5u6zPWAwNnm_JvbFx05yA", "full_address": "Gerwigstrasse 66a\n76131 Karlsruhe", "hours": {"Monday": {"close": "23:00", "open": "06:00"}, "Tuesday": {"close": "23:00", "open": "06:00"}, "Friday": {"close": "22:00", "open": "06:00"}, "Wednesday": {"close": "23:00", "open": "06:00"}, "Thursday": {"close": "23:00", "open": "06:00"}, "Sunday": {"close": "20:00", "open": "10:00"}, "Saturday": {"close": "20:00", "open": "10:00"}}, "open": true, "categories": ["Active Life", "Gyms", "Fitness & Instruction"], "city": "Karlsruhe", "review_count": 8, "name": "Fitness First", "neighborhoods": [], "longitude": 8.43822, "state": "BW", "stars": 2.0, "latitude": 49.00618, "attributes": {"Good for Kids": false, "Price Range": 3}, "type": "business"}
{"business_id": "1t-91ideKB7wTRRmqp3GUA", "full_address": "Gerwigstr. 69\n76131 Karlsruhe", "hours": {"Monday": {"close": "23:00", "open": "07:00"}, "Tuesday": {"close": "23:00", "open": "09:00"}, "Friday": {"close": "23:00", "open": "09:00"}, "Wednesday": {"close": "23:00", "open": "07:00"}, "Thursday": {"close": "23:00", "open": "09:00"}, "Sunday": {"close": "20:00", "open": "10:00"}, "Saturday": {"close": "18:00", "open": "09:00"}}, "open": true, "categories": ["Active Life", "Yoga", "Pilates", "Gyms", "Fitness & Instruction"], "city": "Karlsruhe", "review_count": 3, "name": "ActivSports", "neighborhoods": [], "longitude": 8.4303821, "state": "BW", "stars": 4.0, "latitude": 49.0116951, "attributes": {"Parking": {"garage": false, "validated": false, "street": false, "lot": false, "valet": false}, "Price Range": 1}, "type": "business"}
{"business_id": "VIrt4ovZQRKrUuAelX1Avg", "full_address": "R\u00fcppurrer Str. 1\n76137 Karlsruhe", "hours": {}, "open": true, "categories": ["Active Life", "Pilates", "Gyms", "Fitness & Instruction"], "city": "Karlsruhe", "review_count": 4, "name": "Venice Beach", "neighborhoods": [], "longitude": 8.411515, "state": "BW", "stars": 3.0, "latitude": 49.005771, "attributes": {"Parking": {"garage": false, "validated": false, "street": false, "lot": false, "valet": false}, "Good for Kids": false, "Price Range": 1}, "type": "business"}
{"business_id": "q-Pc4j3mIzCfD-3eOs71jg", "full_address": "Edgar-Heller-Str. 19\n76227 Karlsruhe", "hours": {}, "open": true, "categories": ["Fitness & Instruction", "Police Departments", "Martial Arts", "Active Life", "Public Services & Government", "Sports Clubs"], "city": "Karlsruhe", "review_count": 3, "name": "Polizeisportverein Karlsruhe e.V.", "neighborhoods": [], "longitude": 8.43041, "state": "BW", "stars": 5.0, "latitude": 48.9947, "attributes": {"Good For Dancing": false, "Noise Level": "quiet", "Coat Check": false, "Music": {"dj": false}, "Outdoor Seating": true, "Parking": {"garage": false, "street": false, "validated": false, "lot": false, "valet": false}, "Ambience": {"romantic": false, "intimate": false, "classy": false, "hipster": false, "divey": false, "touristy": false, "trendy": false, "upscale": false, "casual": false}, "Has TV": true, "Accepts Credit Cards": false, "Good for Kids": true, "Good For Groups": true, "Price Range": 1}, "type": "business"}
{"business_id": "mi6HyXkJK9Adzq-xti3oiA", "full_address": "Kaiserallee 3\n76133 Karlsruhe", "hours": {}, "open": false, "categories": ["Active Life", "Dance Studios", "Nightlife", "Dance Clubs", "Fitness & Instruction"], "city": "Karlsruhe", "review_count": 9, "name": "Discothek Unversch\u00e4mt", "neighborhoods": [], "longitude": 8.38676, "state": "BW", "stars": 4.0, "latitude": 49.0103, "attributes": {"Coat Check": true, "Alcohol": "beer_and_wine", "Attire": "casual", "Has TV": false, "Smoking": "outdoor", "Happy Hour": true, "Wheelchair Accessible": true, "Outdoor Seating": false, "Parking": {"garage": false, "validated": false, "street": false, "lot": false, "valet": false}, "Music": {"dj": true, "background_music": false, "karaoke": false, "live": false, "video": false, "jukebox": false}, "Accepts Credit Cards": false, "Good For Groups": false, "Price Range": 2}, "type": "business"}
{"business_id": "G5u6zPWAwNnm_JvbFx05yA", "full_address": "Gerwigstrasse 66a\n76131 Karlsruhe", "hours": {"Monday": {"close": "23:00", "open": "06:00"}, "Tuesday": {"close": "23:00", "open": "06:00"}, "Friday": {"close": "22:00", "open": "06:00"}, "Wednesday": {"close": "23:00", "open": "06:00"}, "Thursday": {"close": "23:00", "open": "06:00"}, "Sunday": {"close": "20:00", "open": "10:00"}, "Saturday": {"close": "20:00", "open": "10:00"}}, "open": true, "categories": ["Active Life", "Gyms", "Fitness & Instruction"], "city": "Karlsruhe", "review_count": 8, "name": "Fitness First", "neighborhoods": [], "longitude": 8.43822, "state": "BW", "stars": 2.0, "latitude": 49.00618, "attributes": {"Good for Kids": false, "Price Range": 3}, "type": "business"}
{"business_id": "1t-91ideKB7wTRRmqp3GUA", "full_address": "Gerwigstr. 69\n76131 Karlsruhe", "hours": {"Monday": {"close": "23:00", "open": "07:00"}, "Tuesday": {"close": "23:00", "open": "09:00"}, "Friday": {"close": "23:00", "open": "09:00"}, "Wednesday": {"close": "23:00", "open": "07:00"}, "Thursday": {"close": "23:00", "open": "09:00"}, "Sunday": {"close": "20:00", "open": "10:00"}, "Saturday": {"close": "18:00", "open": "09:00"}}, "open": true, "categories": ["Active Life", "Yoga", "Pilates", "Gyms", "Fitness & Instruction"], "city": "Karlsruhe", "review_count": 3, "name": "ActivSports", "neighborhoods": [], "longitude": 8.4303821, "state": "BW", "stars": 4.0, "latitude": 49.0116951, "attributes": {"Parking": {"garage": false, "validated": false, "street": false, "lot": false, "valet": false}, "Price Range": 1}, "type": "business"}
{"business_id": "VIrt4ovZQRKrUuAelX1Avg", "full_address": "R\u00fcppurrer Str. 1\n76137 Karlsruhe", "hours": {}, "open": true, "categories": ["Active Life", "Pilates", "Gyms", "Fitness & Instruction"], "city": "Karlsruhe", "review_count": 4, "name": "Venice Beach", "neighborhoods": [], "longitude": 8.411515, "state": "BW", "stars": 3.0, "latitude": 49.005771, "attributes": {"Parking": {"garage": false, "validated": false, "street": false, "lot": false, "valet": false}, "Good for Kids": false, "Price Range": 1}, "type": "business"}
{"business_id": "q-Pc4j3mIzCfD-3eOs71jg", "full_address": "Edgar-Heller-Str. 19\n76227 Karlsruhe", "hours": {}, "open": true, "categories": ["Fitness & Instruction", "Police Departments", "Martial Arts", "Active Life", "Public Services & Government", "Sports Clubs"], "city": "Karlsruhe", "review_count": 3, "name": "Polizeisportverein Karlsruhe e.V.", "neighborhoods": [], "longitude": 8.43041, "state": "BW", "stars": 5.0, "latitude": 48.9947, "attributes": {"Good For Dancing": false, "Noise Level": "quiet", "Coat Check": false, "Music": {"dj": false}, "Outdoor Seating": true, "Parking": {"garage": false, "street": false, "validated": false, "lot": false, "valet": false}, "Ambience": {"romantic": false, "intimate": false, "classy": false, "hipster": false, "divey": false, "touristy": false, "trendy": false, "upscale": false, "casual": false}, "Has TV": true, "Accepts Credit Cards": false, "Good for Kids": true, "Good For Groups": true, "Price Range": 1}, "type": "business"}
{"business_id": "mi6HyXkJK9Adzq-xti3oiA", "full_address": "Kaiserallee 3\n76133 Karlsruhe", "hours": {}, "open": false, "categories": ["Active Life", "Dance Studios", "Nightlife", "Dance Clubs", "Fitness & Instruction"], "city": "Karlsruhe", "review_count": 9, "name": "Discothek Unversch\u00e4mt", "neighborhoods": [], "longitude": 8.38676, "state": "BW", "stars": 4.0, "latitude": 49.0103, "attributes": {"Coat Check": true, "Alcohol": "beer_and_wine", "Attire": "casual", "Has TV": false, "Smoking": "outdoor", "Happy Hour": true, "Wheelchair Accessible": true, "Outdoor Seating": false, "Parking": {"garage": false, "validated": false, "street": false, "lot": false, "valet": false}, "Music": {"dj": true, "background_music": false, "karaoke": false, "live": false, "video": false, "jukebox": false}, "Accepts Credit Cards": false, "Good For Groups": false, "Price Range": 2}, "type": "business"}
{"business_id": "G5u6zPWAwNnm_JvbFx05yA", "full_address": "Gerwigstrasse 66a\n76131 Karlsruhe", "hours": {"Monday": {"close": "23:00", "open": "06:00"}, "Tuesday": {"close": "23:00", "open": "06:00"}, "Friday": {"close": "22:00", "open": "06:00"}, "Wednesday": {"close": "23:00", "open": "06:00"}, "Thursday": {"close": "23:00", "open": "06:00"}, "Sunday": {"close": "20:00", "open": "10:00"}, "Saturday": {"close": "20:00", "open": "10:00"}}, "open": true, "categories": ["Active Life", "Gyms", "Fitness & Instruction"], "city": "Karlsruhe", "review_count": 8, "name": "Fitness First", "neighborhoods": [], "longitude": 8.43822, "state": "BW", "stars": 2.0, "latitude": 49.00618, "attributes": {"Good for Kids": false, "Price Range": 3}, "type": "business"}
{"business_id": "1t-91ideKB7wTRRmqp3GUA", "full_address": "Gerwigstr. 69\n76131 Karlsruhe", "hours": {"Monday": {"close": "23:00", "open": "07:00"}, "Tuesday": {"close": "23:00", "open": "09:00"}, "Friday": {"close": "23:00", "open": "09:00"}, "Wednesday": {"close": "23:00", "open": "07:00"}, "Thursday": {"close": "23:00", "open": "09:00"}, "Sunday": {"close": "20:00", "open": "10:00"}, "Saturday": {"close": "18:00", "open": "09:00"}}, "open": true, "categories": ["Active Life", "Yoga", "Pilates", "Gyms", "Fitness & Instruction"], "city": "Karlsruhe", "review_count": 3, "name": "ActivSports", "neighborhoods": [], "longitude": 8.4303821, "state": "BW", "stars": 4.0, "latitude": 49.0116951, "attributes": {"Parking": {"garage": false, "validated": false, "street": false, "lot": false, "valet": false}, "Price Range": 1}, "type": "business"}
{"business_id": "VIrt4ovZQRKrUuAelX1Avg", "full_address": "R\u00fcppurrer Str. 1\n76137 Karlsruhe", "hours": {}, "open": true, "categories": ["Active Life", "Pilates", "Gyms", "Fitness & Instruction"], "city": "Karlsruhe", "review_count": 4, "name": "Venice Beach", "neighborhoods": [], "longitude": 8.411515, "state": "BW", "stars": 3.0, "latitude": 49.005771, "attributes": {"Parking": {"garage": false, "validated": false, "street": false, "lot": false, "valet": false}, "Good for Kids": false, "Price Range": 1}, "type": "business"}
{"business_id": "q-Pc4j3mIzCfD-3eOs71jg", "full_address": "Edgar-Heller-Str. 19\n76227 Karlsruhe", "hours": {}, "open": true, "categories": ["Fitness & Instruction", "Police Departments", "Martial Arts", "Active Life", "Public Services & Government", "Sports Clubs"], "city": "Karlsruhe", "review_count": 3, "name": "Polizeisportverein Karlsruhe e.V.", "neighborhoods": [], "longitude": 8.43041, "state": "BW", "stars": 5.0, "latitude": 48.9947, "attributes": {"Good For Dancing": false, "Noise Level": "quiet", "Coat Check": false, "Music": {"dj": false}, "Outdoor Seating": true, "Parking": {"garage": false, "street": false, "validated": false, "lot": false, "valet": false}, "Ambience": {"romantic": false, "intimate": false, "classy": false, "hipster": false, "divey": false, "touristy": false, "trendy": false, "upscale": false, "casual": false}, "Has TV": true, "Accepts Credit Cards": false, "Good for Kids": true, "Good For Groups": true, "Price Range": 1}, "type": "business"}
{"business_id": "mi6HyXkJK9Adzq-xti3oiA", "full_address": "Kaiserallee 3\n76133 Karlsruhe", "hours": {}, "open": false, "categories": ["Active Life", "Dance Studios", "Nightlife", "Dance Clubs", "Fitness & Instruction"], "city": "Karlsruhe", "review_count": 9, "name": "Discothek Unversch\u00e4mt", "neighborhoods": [], "longitude": 8.38676, "state": "BW", "stars": 4.0, "latitude": 49.0103, "attributes": {"Coat Check": true, "Alcohol": "beer_and_wine", "Attire": "casual", "Has TV": false, "Smoking": "outdoor", "Happy Hour": true, "Wheelchair Accessible": true, "Outdoor Seating": false, "Parking": {"garage": false, "validated": false, "street": false, "lot": false, "valet": false}, "Music": {"dj": true, "background_music": false, "karaoke": false, "live": false, "video": false, "jukebox": false}, "Accepts Credit Cards": false, "Good For Groups": false, "Price Range": 2}, "type": "business"}
{"business_id": "G5u6zPWAwNnm_JvbFx05yA", "full_address": "Gerwigstrasse 66a\n76131 Karlsruhe", "hours": {"Monday": {"close": "23:00", "open": "06:00"}, "Tuesday": {"close": "23:00", "open": "06:00"}, "Friday": {"close": "22:00", "open": "06:00"}, "Wednesday": {"close": "23:00", "open": "06:00"}, "Thursday": {"close": "23:00", "open": "06:00"}, "Sunday": {"close": "20:00", "open": "10:00"}, "Saturday": {"close": "20:00", "open": "10:00"}}, "open": true, "categories": ["Active Life", "Gyms", "Fitness & Instruction"], "city": "Karlsruhe", "review_count": 8, "name": "Fitness First", "neighborhoods": [], "longitude": 8.43822, "state": "BW", "stars": 2.0, "latitude": 49.00618, "attributes": {"Good for Kids": false, "Price Range": 3}, "type": "business"}
{"business_id": "1t-91ideKB7wTRRmqp3GUA", "full_address": "Gerwigstr. 69\n76131 Karlsruhe", "hours": {"Monday": {"close": "23:00", "open": "07:00"}, "Tuesday": {"close": "23:00", "open": "09:00"}, "Friday": {"close": "23:00", "open": "09:00"}, "Wednesday": {"close": "23:00", "open": "07:00"}, "Thursday": {"close": "23:00", "open": "09:00"}, "Sunday": {"close": "20:00", "open": "10:00"}, "Saturday": {"close": "18:00", "open": "09:00"}}, "open": true, "categories": ["Active Life", "Yoga", "Pilates", "Gyms", "Fitness & Instruction"], "city": "Karlsruhe", "review_count": 3, "name": "ActivSports", "neighborhoods": [], "longitude": 8.4303821, "state": "BW", "stars": 4.0, "latitude": 49.0116951, "attributes": {"Parking": {"garage": false, "validated": false, "street": false, "lot": false, "valet": false}, "Price Range": 1}, "type": "business"}
{"business_id": "VIrt4ovZQRKrUuAelX1Avg", "full_address": "R\u00fcppurrer Str. 1\n76137 Karlsruhe", "hours": {}, "open": true, "categories": ["Active Life", "Pilates", "Gyms", "Fitness & Instruction"], "city": "Karlsruhe", "review_count": 4, "name": "Venice Beach", "neighborhoods": [], "longitude": 8.411515, "state": "BW", "stars": 3.0, "latitude": 49.005771, "attributes": {"Parking": {"garage": false, "validated": false, "street": false, "lot": false, "valet": false}, "Good for Kids": false, "Price Range": 1}, "type": "business"}
